include_pandoc/__init__.py
include_pandoc/addargs.py
include_pandoc/createaddargs.py
include_pandoc/process_includes.py
include_pandoc-0.11.data/scripts/include-pandoc
include_pandoc-0.11.dist-info/LICENSE
include_pandoc-0.11.dist-info/METADATA
include_pandoc-0.11.dist-info/WHEEL
include_pandoc-0.11.dist-info/top_level.txt
include_pandoc-0.11.dist-info/RECORD
