Metadata-Version: 2.1
Name: include-pandoc
Version: 0.11
Summary: A wrapper for pandoc to pre-process includes (even nested ones)
Home-page: https://github.com/alpianon/include-pandoc
Author: Alberto Pianon
Author-email: pianon@array.eu
License: UNKNOWN
Platform: UNKNOWN
Classifier: Programming Language :: Python :: 2.7
Classifier: License :: OSI Approved :: GNU General Public License v3 (GPLv3) 
Classifier: Operating System :: OS Independent
Requires-Dist: argparse
